LICENSE
README.md
pip-requires
setup.py
tests.py
tox.ini
cloudslave/__init__.py
cloudslave/exc.py
cloudslave/models.py
cloudslave/tests.py
cloudslave/testsettings.py
cloudslave/fixtures/test-ssh-key
cloudslave/fixtures/test-ssh-key.pub
cloudslave/fixtures/test_cloud.yaml
cloudslave/migrations/0001_initial.py
cloudslave/migrations/0002_auto__add_field_slave_floating_ip.py
cloudslave/migrations/__init__.py
django_cloudslave.egg-info/PKG-INFO
django_cloudslave.egg-info/SOURCES.txt
django_cloudslave.egg-info/dependency_links.txt
django_cloudslave.egg-info/requires.txt
django_cloudslave.egg-info/top_level.txt