Metadata-Version: 1.1
Name: django-cloudslave
Version: 0.2.2
Summary: Create, use and destroy temporary slaves in the cloud
Home-page: http://github.com/sorenh/python-django-cloudslave
Author: Soren Hansen
Author-email: sorhanse@cisco.com
License: Apache 2.0
Keywords: django openstack cloud
Platform: UNKNOWN
Classifier: Development Status :: 2 - Pre-Alpha
Classifier: Environment :: Web Environment
Classifier: Framework :: Django
Classifier: Intended Audience :: Developers
Classifier: License :: OSI Approved :: Apache Software License
Classifier: Operating System :: POSIX :: Linux
Classifier: Programming Language :: Python
Classifier: Topic :: Software Development
